mjxcore.cpython-39-x86_64-linux-gnu.so
mjxcore-0.0.1.dist-info/top_level.txt
mjxcore-0.0.1.dist-info/WHEEL
mjxcore-0.0.1.dist-info/METADATA
mjxcore-0.0.1.dist-info/RECORD
