Metadata-Version: 2.1
Name: mjxcore
Version: 0.0.1
Summary: UNKNOWN
Home-page: UNKNOWN
Author: Mjx Project Team
Author-email: koyamada-s@sys.i.kyoto-u.ac.jp
License: UNKNOWN
Platform: UNKNOWN
Provides-Extra: test
Requires-Dist: pytest ; extra == 'test'
